CHANGES.txt
MANIFEST.in
README.rst
setup.py
urwid_pydux/__init__.py
urwid_pydux/urwid_pydux.py
urwid_pydux.egg-info/PKG-INFO
urwid_pydux.egg-info/SOURCES.txt
urwid_pydux.egg-info/dependency_links.txt
urwid_pydux.egg-info/requires.txt
urwid_pydux.egg-info/top_level.txt